{
  "kind": "bench",
  "framework": "alien-v3",
  "suites": [
    "kairo",
    "sbench"
  ],
  "timestamp": "2026-07-03T20-46-07",
  "node": "v24.16.0",
  "loadavg": [
    5.10498046875,
    4.99755859375,
    4.71484375
  ],
  "ok": true,
  "error": null,
  "rows": [
    {
      "suite": "kairo",
      "framework": "alien-v3",
      "test": "avoidablePropagation",
      "time": 96.18154099999998
    },
    {
      "suite": "kairo",
      "framework": "alien-v3",
      "test": "broadPropagation",
      "time": 75.436375
    },
    {
      "suite": "kairo",
      "framework": "alien-v3",
      "test": "deepPropagation",
      "time": 31.337582999999995
    },
    {
      "suite": "kairo",
      "framework": "alien-v3",
      "test": "diamond",
      "time": 79.15433299999995
    },
    {
      "suite": "kairo",
      "framework": "alien-v3",
      "test": "mux",
      "time": 80.49508300000025
    },
    {
      "suite": "kairo",
      "framework": "alien-v3",
      "test": "repeatedObservers",
      "time": 11.71466700000019
    },
    {
      "suite": "kairo",
      "framework": "alien-v3",
      "test": "triangle",
      "time": 25.903208000000177
    },
    {
      "suite": "kairo",
      "framework": "alien-v3",
      "test": "unstable",
      "time": 12.480457999999999
    },
    {
      "suite": "kairo",
      "framework": "alien-v3",
      "test": "molBench",
      "time": 13.587250000000495
    },
    {
      "suite": "sbench",
      "framework": "alien-v3",
      "test": "createSignals",
      "time": 3.7384169999999983
    },
    {
      "suite": "sbench",
      "framework": "alien-v3",
      "test": "createComputations",
      "time": 70.33995800000008
    },
    {
      "suite": "sbench",
      "framework": "alien-v3",
      "test": "updateSignals",
      "time": 307.2009160000009
    }
  ]
}
